AUTHORS.md
CHANGELOG.md
CONTRIBUTING.md
LICENSE
MANIFEST.in
README.md
pyproject.toml
setup.cfg
setup.py
grond.egg-info/PKG-INFO
grond.egg-info/SOURCES.txt
grond.egg-info/dependency_links.txt
grond.egg-info/entry_points.txt
grond.egg-info/requires.txt
grond.egg-info/top_level.txt
maintenance/pip/readme.rst
src/__init__.py
src/config.py
src/core.py
src/dataset.py
src/environment.py
src/info.py
src/meta.py
src/monitor.py
src/qc.py
src/run_info.py
src/scenario.py
src/stats.py
src/synthetic_tests.py
src/toy.py
src/upgrade.py
src/version.py
src/analysers/__init__.py
src/analysers/base.py
src/analysers/noise_analyser/__init__.py
src/analysers/noise_analyser/analyser.py
src/analysers/target_balancing/__init__.py
src/analysers/target_balancing/analyser.py
src/apps/__init__.py
src/apps/cmd_init.py
src/apps/grond.py
src/clustering/__init__.py
src/clustering/dbscan.py
src/clustering/metrics.py
src/data/examples/example_insar/README.md
src/data/examples/example_insar/bin/download_gf_stores.sh
src/data/examples/example_insar/bin/download_insar_data.sh
src/data/examples/example_insar/config/insar_rectangular.gronf
src/data/examples/example_insar_gnss/README.md
src/data/examples/example_insar_gnss/bin/download_data.sh
src/data/examples/example_insar_gnss/bin/download_gf_stores.sh
src/data/examples/example_insar_gnss/config/insar_rectangular.gronf
src/data/examples/example_landslide/bin/download_gf_stores.sh
src/data/examples/example_landslide/bin/grondown
src/data/examples/example_landslide/bin/grondown.command
src/data/examples/example_landslide/config/example_landslide.gronf
src/data/examples/example_regional_cmt/README.md
src/data/examples/example_regional_cmt/bin/download_gf_stores.sh
src/data/examples/example_regional_cmt/bin/grondown
src/data/examples/example_regional_cmt/bin/grondown_regional.sh
src/data/examples/example_regional_cmt/config/regional_cmt.gronf
src/data/examples/example_wphase/README.md
src/data/examples/example_wphase/bin/download_gf_stores.sh
src/data/examples/example_wphase/bin/grondown
src/data/examples/example_wphase/bin/grondown_wphase.sh
src/data/examples/example_wphase/config/wphase_cmt.gronf
src/data/snippets/README.md
