Metadata-Version: 2.1
Name: grond
Version: 1.8.0
Summary: A probabilistic earthquake source inversion framework. Designed and crafted in Mordor.
Author-email: The Grond Developers <info@pyrocko.org>
Maintainer-email: Sebastian Heimann <sebastian.heimann@uni-potsdam.de>
License: GPLv3
Project-URL: homepage, https://pyrocko.org/grond
Project-URL: documentation, https://pyrocko.org/grond
Project-URL: repository, https://git.pyrocko.org/pyrocko/grond
Project-URL: changelog, https://git.pyrocko.org/pyrocko/grond/src/branch/main/CHANGELOG.md
Keywords: seismology,waveform analysis,earthquake modelling,geophysics,geophysical inversion
Classifier: License :: OSI Approved :: GNU General Public License v3 (GPLv3)
Classifier: Development Status :: 5 - Production/Stable
Classifier: Intended Audience :: Science/Research
Classifier: Programming Language :: Python :: 3
Classifier: Programming Language :: Python :: Implementation :: CPython
Classifier: Operating System :: POSIX
Classifier: Operating System :: MacOS
Classifier: Topic :: Scientific/Engineering
Classifier: Topic :: Scientific/Engineering :: Physics
Classifier: Topic :: Scientific/Engineering :: Visualization
Classifier: Topic :: Scientific/Engineering :: Information Analysis
Classifier: Topic :: Software Development :: Libraries :: Application Frameworks
Requires-Python: >=3.10
Provides-Extra: insar
License-File: LICENSE
License-File: AUTHORS.md
